{
 "cells": [
  {
   "cell_type": "code",
   "execution_count": 1,
   "metadata": {},
   "outputs": [
    {
     "name": "stdout",
     "output_type": "stream",
     "text": [
      "  5           0 LOAD_FAST                0 (a)\n",
      "              2 LOAD_FAST                1 (b)\n",
      "              4 BINARY_ADD\n",
      "              6 STORE_FAST               2 (c)\n",
      "\n",
      "  6           8 LOAD_FAST                2 (c)\n",
      "             10 RETURN_VALUE\n"
     ]
    }
   ],
   "source": [
    "import dis\n",
    "\n",
    "\n",
    "def add(a,b):\n",
    "    c = a + b\n",
    "    return c\n",
    "\n",
    "dis.dis(add)"
   ]
  },
  {
   "cell_type": "code",
   "execution_count": 2,
   "metadata": {},
   "outputs": [
    {
     "name": "stdout",
     "output_type": "stream",
     "text": [
      "  2           0 LOAD_FAST                0 (a)\n",
      "              2 LOAD_FAST                1 (b)\n",
      "              4 BINARY_ADD\n",
      "              6 RETURN_VALUE\n"
     ]
    }
   ],
   "source": [
    "def add(a,b):\n",
    "    return a+b\n",
    "\n",
    "dis.dis(add)"
   ]
  },
  {
   "cell_type": "code",
   "execution_count": 3,
   "metadata": {},
   "outputs": [
    {
     "name": "stdout",
     "output_type": "stream",
     "text": [
      "  2           0 LOAD_FAST                0 (a)\n",
      "              2 LOAD_FAST                1 (b)\n",
      "              4 BINARY_ADD\n",
      "              6 STORE_FAST               2 (c)\n",
      "\n",
      "  3           8 LOAD_FAST                0 (a)\n",
      "             10 LOAD_FAST                1 (b)\n",
      "             12 BINARY_ADD\n",
      "             14 RETURN_VALUE\n"
     ]
    }
   ],
   "source": [
    "def add(a,b):\n",
    "    c = a + b\n",
    "    return a+b\n",
    "\n",
    "dis.dis(add)"
   ]
  },
  {
   "cell_type": "code",
   "execution_count": null,
   "metadata": {},
   "outputs": [],
   "source": []
  }
 ],
 "metadata": {
  "kernelspec": {
   "display_name": "Python 3",
   "language": "python",
   "name": "python3"
  },
  "language_info": {
   "codemirror_mode": {
    "name": "ipython",
    "version": 3
   },
   "file_extension": ".py",
   "mimetype": "text/x-python",
   "name": "python",
   "nbconvert_exporter": "python",
   "pygments_lexer": "ipython3",
   "version": "3.8.5"
  }
 },
 "nbformat": 4,
 "nbformat_minor": 4
}
